pydf2json/__init__.py
pydf2json/pdfcrypt.py
pydf2json/pydf2json.py
pydf2json/scripts/__init__.py
pydf2json/scripts/pdfcrack.py
pydf2json/scripts/pydf.py
pydf2json-2.4.0.dist-info/LICENSE
pydf2json-2.4.0.dist-info/METADATA
pydf2json-2.4.0.dist-info/WHEEL
pydf2json-2.4.0.dist-info/entry_points.txt
pydf2json-2.4.0.dist-info/top_level.txt
pydf2json-2.4.0.dist-info/RECORD
