Metadata-Version: 2.1
Name: pydf2json
Version: 2.4.0
Summary: PDF analysis. Convert contents of PDF to a JSON-style python dictionary.
Home-page: https://github.com/kingaling/pydf2json
Author: Shane King
Author-email: kinagling@meatchicken.net
License: GPL-3.0
Keywords: pdf,pydf2json,pdf analysis,python,python pdf,pdf crack,laikaboss
Platform: UNKNOWN
Classifier: Development Status :: 3 - Alpha
Classifier: Intended Audience :: Information Technology
Classifier: License :: OSI Approved :: GNU General Public License v3 (GPLv3)
Classifier: Natural Language :: English
Classifier: Operating System :: MacOS
Classifier: Operating System :: Microsoft :: Windows :: Windows 7
Classifier: Operating System :: Microsoft :: Windows :: Windows 10
Classifier: Operating System :: POSIX :: Linux
Classifier: Programming Language :: Python :: 2.7
Classifier: Topic :: Scientific/Engineering :: Information Analysis
Classifier: Topic :: Security
Requires-Python: >=2.6, <3
